ELEC4200/lab9/Extra/Lab9/Lab9/Lab9.srcs/sources_1/new/five_ring.v
`timescale 1ns / 1ps
//////////////////////////////////////////////////////////////////////////////////
// Company: 
// Engineer: 
// 
// Create Date: 10/23/2021 12:22:56 PM
// Design Name: 
// Module Name: five_ring
// Project Name: 
// Target Devices: 
// Tool Versions: 
// Description: 
// 
// Dependencies: 
// 
// Revision:
// Revision 0.01 - File Created
// Additional Comments:
// 
//////////////////////////////////////////////////////////////////////////////////
/*
(* DONT_TOUCH = "TRUE" *)
(* ALLOW_COMBINATIONAL_LOOPS = "TRUE" *)

*/

module five_ring(enable,out);
    input enable;
    output out;
    //output w1, w2, w3, w4, w5, w6, out;
    (* ALLOW_COMBINATIONAL_LOOPS = "TRUE" *)
    (* DONT_TOUCH = "TRUE" *) wire w1, w2, w3, w4, w5, w6;
    
    //input enable;
    //output w1, w2, w3, w4, w5, w6, Q;
    
    assign out = w6;
    and #5(w1, enable,out );   
    not #5(w2, w1);
    not #5(w3, w2);
    not #5(w4, w3);
    not #5(w5, w4);
    not #5(w6,w5);
    
    
    
    
    
    
endmodule

ELEC4200/lab9/Extra/Lab9/Lab9/Lab9.srcs/sim_1/new/five_ring_sim.v
`timescale 1ns / 1ps
//////////////////////////////////////////////////////////////////////////////////
// Company: 
// Engineer: 
// 
// Create Date: 10/23/2021 12:40:01 PM
// Design Name: 
// Module Name: five_ring_sim
// Project Name: 
// Target Devices: 
// Tool Versions: 
// Description: 
// 
// Dependencies: 
// 
// Revision:
// Revision 0.01 - File Created
// Additional Comments:
// 
//////////////////////////////////////////////////////////////////////////////////


module five_ring_sim(
    );
	reg enable;
	wire out;
	/*
	wire w1; 
	wire w2;
	wire w3;
	wire w4;
	wire w5;
	wire w6;
	*/
	
	
	
	
 
    //five_ring DUT ( .enable(enable), .w1(w1), .w2(w2), .w3(w3), .w4(w4), .w5(w5), .w6(w6), .out(out) ); 
    five_ring DUT ( .enable(enable), .out(out) );   
    initial begin
    $dumpfile("dump.vcd");
    $dumpvars(1);
    enable = 1'b?;
    #1000 enable = 1'b0;
    #150 enable = 1'b1;
    #450 $stop;
    end
    /*
    initial begin
    enable = 1'b0;
    #1000
    enable = 1'b1;
    end
    */
endmodule

ELEC4200/lab9/Extra/Lab9/Lab9/Lab9.sim/sim_1/behav/xsim/dump.vcd
$date
   Sat Oct 23 16:34:20 2021
$end
$version
  2020.2
$end
$timescale
  1ps
$end
$scope module five_ring_sim $end
$var reg 1 ! enable $end
$var wire 1 " out $end
$upscope $end
$enddefinitions $end
#0
$dumpvars
z!
x"
$end
#5000
x"
#1000000
0!
#1030000
1"
#1150000
1!
#1180000
0"
#1210000
1"
#1240000
0"
#1270000
1"
#1300000
0"
#1330000
1"
#1360000
0"
#1390000
1"
#1420000
0"
#1450000
1"
#1480000
0"
#1510000
1"
#1540000
0"
#1570000
1"
#1600000
0"
